xia_coder/__init__.py
xia_coder/coder.cpython-311-darwin.so
xia_coder-0.0.9.dist-info/LICENSE.txt
xia_coder-0.0.9.dist-info/METADATA
xia_coder-0.0.9.dist-info/WHEEL
xia_coder-0.0.9.dist-info/top_level.txt
xia_coder-0.0.9.dist-info/RECORD
