Metadata-Version: 2.1
Name: xia-coder
Version: 0.0.9
Summary: UNKNOWN
Home-page: https://develop.x-i-a.com/docs/xia-coder/0.0.9/index.html
Author: X-I-A
Author-email: admin@x-i-a.com
License: UNKNOWN
Platform: UNKNOWN
Requires-Python: >=3.9
License-File: LICENSE.txt
Requires-Dist: xia-engine
